<?xml version="1.0" encoding="UTF-8"?><record_update table="ais_search_profile_ais_dictionary_m2m">
    <ais_search_profile_ais_dictionary_m2m action="INSERT_OR_UPDATE">
        <dictionary display_value="default_stop_word_dictionary">9865058bc7031010d1cfd9795cc26037</dictionary>
        <dictionary_reference_qualifier/>
        <marked_for_deletion>false</marked_for_deletion>
        <profile display_value="COS View search profile">34a9a3ecbb4431102a88136481dca0cb</profile>
        <sys_class_name>ais_search_profile_ais_dictionary_m2m</sys_class_name>
        <sys_created_by>admin</sys_created_by>
        <sys_created_on>2023-07-12 14:34:17</sys_created_on>
        <sys_id>7ca9a3ec06443110e12874ae544e74c5</sys_id>
        <sys_mod_count>0</sys_mod_count>
        <sys_name>default_stop_word_dictionary.COS View search profile</sys_name>
        <sys_package display_value="Awards App" source="x_snc_awards_app">d2859facfcc031107f449da0d8575079</sys_package>
        <sys_policy/>
        <sys_scope display_value="Awards App">d2859facfcc031107f449da0d8575079</sys_scope>
        <sys_update_name>ais_search_profile_ais_dictionary_m2m_7ca9a3ec06443110e12874ae544e74c5</sys_update_name>
        <sys_updated_by>admin</sys_updated_by>
        <sys_updated_on>2023-07-12 14:34:17</sys_updated_on>
    </ais_search_profile_ais_dictionary_m2m>
</record_update>
